label_chess/VERSION
label_chess/__init__.py
label_chess/app.py
label_chess/base.py
label_chess/models.py
label_chess/pgn2imgs.py
label_chess/utils.py
label_chess/controllers/__init__.py
label_chess/controllers/annotate.py
label_chess/controllers/load.py
label_chess/views/__init__.py
label_chess/views/annotate.py
label_chess/views/config.py
label_chess/views/export.py
label_chess/views/load.py
label_chess-0.0.5.dist-info/LICENSE
label_chess-0.0.5.dist-info/METADATA
label_chess-0.0.5.dist-info/WHEEL
label_chess-0.0.5.dist-info/top_level.txt
label_chess-0.0.5.dist-info/RECORD
