Metadata-Version: 2.1
Name: label-chess
Version: 0.0.5
Summary: Desktop app to annotate chessgames
Home-page: https://github.com/elbuco1/label_chess
Author: Laurent Boucaud
Author-email: lrtboucaud@gmail.com
License: UNKNOWN
Platform: UNKNOWN
Classifier: License :: OSI Approved :: MIT License
Classifier: Programming Language :: Python :: 3.7
Classifier: Programming Language :: Python :: 3.8
Classifier: Programming Language :: Python :: 3.9
Classifier: Programming Language :: Python :: 3 :: Only
Requires-Python: >=3.7,<3.10
License-File: LICENSE
Requires-Dist: pandas (<1.2,>=1.1)
Requires-Dist: opencv-python (<4.6,>=4.5)
Requires-Dist: chess (<1.5,>=1.4)
Requires-Dist: sqlalchemy (<1.5,>1.4)
Requires-Dist: Pillow (<8.2,>=8.1.2)
Requires-Dist: fen2pil (>=0.0.1)
Requires-Dist: youtube-dl
Requires-Dist: requests
